LICENSE
README.md
setup.py
kanodev/__init__.py
kanodev/kanodev.py
kanodev.egg-info/PKG-INFO
kanodev.egg-info/SOURCES.txt
kanodev.egg-info/dependency_links.txt
kanodev.egg-info/entry_points.txt
kanodev.egg-info/requires.txt
kanodev.egg-info/top_level.txt
kanodev/src/__init__.py
kanodev/src/utils/__init__.py
kanodev/src/utils/chat_utils.py
kanodev/src/utils/general_utils.py