Metadata-Version: 2.1
Name: kanodev
Version: 0.1.0
Summary: Use natural language to create a fully functional, tested and deployed cloud infrastructure with a single command!
Author: KanoScale
Author-email: <info@kanoscale.com>
Keywords: GPT,AWS,Cloud,Infrastructure,Natural Language,OpenAI,KanoScale,KanoDev,Kano
Classifier: Development Status :: 1 - Planning
Classifier: Intended Audience :: Developers
Classifier: Programming Language :: Python :: 3
Classifier: Operating System :: Unix
Classifier: Operating System :: MacOS :: MacOS X
Classifier: Operating System :: Microsoft :: Windows
License-File: LICENSE
